ourtest/__init__.py
ourtest/config.txt
ourtest/hello.py
udacity_CarNDT1Test-1.1.0.dist-info/METADATA
udacity_CarNDT1Test-1.1.0.dist-info/WHEEL
udacity_CarNDT1Test-1.1.0.dist-info/top_level.txt
udacity_CarNDT1Test-1.1.0.dist-info/RECORD
